README.md
diqu/__init__.py
diqu/alerts/__init__.py
diqu/alerts/sendgrid.py
diqu_email-1.0.0.dist-info/LICENSE
diqu_email-1.0.0.dist-info/METADATA
diqu_email-1.0.0.dist-info/WHEEL
diqu_email-1.0.0.dist-info/RECORD
